{
    "Name": "<b><i><color=Lime>[РЕДАКТОР]</a></i> - <color=Red>Редактируйте, создавайте собственные карты, в одиночку или с друзьями!</a></b>",
    "Description": "<b><i>!Создавай собственные карты, или редактируйте их!</i></b>",
    "StartClientVersion": 334,
    "ApiVersion": 2,
    "MapLists": [
      {
        "MapListId": 8401,
        "Name": "Заготовки"
      }
    ],
    "Parameters": {
      "Bool": [
        {
          "Name": "Damage",
          "DisplayName": "<b><color=Lime>УРОН</a> на сервере|",
          "Default": true
        },
        {
          "Name": "BlueTeam",
          "DisplayName": "КОМАНДА СИНИЯ",
          "Default": true
        }
      ]
    }
}
